{"materialDefinitions":{"Mat4020":{"name":"standard","type":"standard","params":{"renderMode":"solid","shininess":1,"reflectivity":0,"ambient":[1,1,1,1],"diffuse":[0,0,0,1],"specular":[0.00007843137254901961,0.00007843137254901961,0.00007843137254901961,1],"useVertexColorAlpha":false,"vertexRegions":false,"vertexColors":true}},"Mat4021":{"name":"standard","type":"standard","params":{"renderMode":"solid","shininess":1,"reflectivity":0,"ambient":[1,1,1,1],"diffuse":[0,0,0,1],"specular":[0.00007843137254901961,0.00007843137254901961,0.00007843137254901961,1],"useVertexColorAlpha":false,"vertexRegions":false,"vertexColors":true}},"Mat4022":{"name":"standard","type":"standard","params":{"renderMode":"solid","shininess":1,"reflectivity":0,"ambient":[1,1,1,1],"diffuse":[0,0,0,1],"specular":[0.00007843137254901961,0.00007843137254901961,0.00007843137254901961,1],"useVertexColorAlpha":false,"vertexRegions":false,"vertexColors":true}},"Mat4023":{"name":"standard","type":"standard","params":{"renderMode":"solid","shininess":1,"reflectivity":0,"ambient":[1,1,1,1],"diffuse":[0,0,0,1],"specular":[0.00007843137254901961,0.00007843137254901961,0.00007843137254901961,1],"useVertexColorAlpha":false,"vertexRegions":false,"vertexColors":true}},"Mat4024":{"name":"standard","type":"standard","params":{"renderMode":"solid","shininess":1,"reflectivity":0,"ambient":[1,1,1,1],"diffuse":[0.3999372549019608,0.3999372549019608,0.3999372549019608,1],"specular":[0.400078431372549,0.400078431372549,0.400078431372549,1],"useVertexColorAlpha":false,"vertexRegions":false,"vertexColors":true}}},"textureDefinitions":{"4020":{"encoding":["image/jpeg"],"wrap":["none"],"atlas":false,"uvSet":"uv0","channels":"rgb","images":[{"id":"1155155845378474387","size":128,"href":["../textures/0"],"length":[16384]}]},"4021":{"encoding":["image/jpeg"],"wrap":["none"],"atlas":false,"uvSet":"uv0","channels":"rgb","images":[{"id":"1161912206892204435","size":512,"href":["../textures/0"],"length":[524288]}]},"4022":{"encoding":["image/jpeg"],"wrap":["none"],"atlas":false,"uvSet":"uv0","channels":"rgb","images":[{"id":"1155155845378474387","size":128,"href":["../textures/0"],"length":[16384]}]},"4023":{"encoding":["image/jpeg"],"wrap":["none"],"atlas":false,"uvSet":"uv0","channels":"rgb","images":[{"id":"1155156807451148691","size":128,"href":["../textures/0"],"length":[131072]}]}}}